{
  "scan_time": "2026-07-12T16:59:46.483865+00:00",
  "assets_scanned": 55,
  "signals_count": 0,
  "duration_s": 48.08,
  "signals": [],
  "leaderboard": [
    {
      "symbol": "ADI/USDT",
      "score": 64.2,
      "trend": 100.0,
      "momentum": 59.38,
      "liquidity": 30.5,
      "wall_signal": false,
      "price": 6.8865
    },
    {
      "symbol": "LTC/USD",
      "score": 63.88,
      "trend": 100.0,
      "momentum": 14.75,
      "liquidity": 28.07,
      "wall_signal": true,
      "price": 44.78
    },
    {
      "symbol": "DEXE/USDT",
      "score": 62.99,
      "trend": 100.0,
      "momentum": 75.0,
      "liquidity": 11.25,
      "wall_signal": false,
      "price": 47.5835
    },
    {
      "symbol": "ZEC/USDT",
      "score": 58.82,
      "trend": 100.0,
      "momentum": 51.64,
      "liquidity": 30.02,
      "wall_signal": false,
      "price": 543.21
    },
    {
      "symbol": "ZEC/USD",
      "score": 57.9,
      "trend": 100.0,
      "momentum": 51.6,
      "liquidity": 24.12,
      "wall_signal": false,
      "price": 542.7
    },
    {
      "symbol": "BTC/USD",
      "score": 56.69,
      "trend": 100.0,
      "momentum": 11.2,
      "liquidity": 19.91,
      "wall_signal": true,
      "price": 64138.65
    },
    {
      "symbol": "WLD/USD",
      "score": 56.69,
      "trend": 38.38,
      "momentum": 52.76,
      "liquidity": 26.23,
      "wall_signal": true,
      "price": 0.4311
    },
    {
      "symbol": "BILL/USDT",
      "score": 54.21,
      "trend": 55.0,
      "momentum": 72.09,
      "liquidity": 34.25,
      "wall_signal": false,
      "price": 0.04874
    },
    {
      "symbol": "AAVE/USDT",
      "score": 53.85,
      "trend": 100.0,
      "momentum": 30.49,
      "liquidity": 28.62,
      "wall_signal": false,
      "price": 99.198
    },
    {
      "symbol": "ARB/USDT",
      "score": 53.73,
      "trend": 100.0,
      "momentum": 33.76,
      "liquidity": 23.87,
      "wall_signal": false,
      "price": 0.09509
    },
    {
      "symbol": "LIGHTER/USD",
      "score": 52.39,
      "trend": 100.0,
      "momentum": 36.43,
      "liquidity": 17.98,
      "wall_signal": false,
      "price": 2.666
    },
    {
      "symbol": "LINK/USDT",
      "score": 51.96,
      "trend": 81.22,
      "momentum": 15.74,
      "liquidity": 24.97,
      "wall_signal": true,
      "price": 8.0685
    },
    {
      "symbol": "UNI/USDT",
      "score": 51.87,
      "trend": 100.0,
      "momentum": 30.99,
      "liquidity": 26.84,
      "wall_signal": false,
      "price": 3.6674
    },
    {
      "symbol": "LIT/USDT",
      "score": 51.69,
      "trend": 100.0,
      "momentum": 36.54,
      "liquidity": 21.24,
      "wall_signal": false,
      "price": 2.6686
    },
    {
      "symbol": "AAVE/USD",
      "score": 51.65,
      "trend": 100.0,
      "momentum": 30.5,
      "liquidity": 20.82,
      "wall_signal": false,
      "price": 99.1
    },
    {
      "symbol": "UNI/USD",
      "score": 50.9,
      "trend": 100.0,
      "momentum": 31.33,
      "liquidity": 20.28,
      "wall_signal": false,
      "price": 3.669
    },
    {
      "symbol": "PEPE/USDT",
      "score": 50.81,
      "trend": 81.94,
      "momentum": 23.33,
      "liquidity": 53.95,
      "wall_signal": false,
      "price": 2.785e-06
    },
    {
      "symbol": "LTC/USDT",
      "score": 48.53,
      "trend": 80.51,
      "momentum": 14.61,
      "liquidity": 14.88,
      "wall_signal": true,
      "price": 44.79
    },
    {
      "symbol": "OKB/USDT",
      "score": 47.76,
      "trend": 100.0,
      "momentum": 12.4,
      "liquidity": 18.97,
      "wall_signal": false,
      "price": 80.71
    },
    {
      "symbol": "LINK/USD",
      "score": 46.69,
      "trend": 100.0,
      "momentum": 15.74,
      "liquidity": 21.71,
      "wall_signal": false,
      "price": 8.062
    }
  ]
}