{
  "scan_time": "2026-07-14T09:59:32.627950+00:00",
  "assets_scanned": 61,
  "signals_count": 0,
  "duration_s": 53.26,
  "signals": [],
  "leaderboard": [
    {
      "symbol": "BILL/USDT",
      "score": 62.97,
      "trend": 80.0,
      "momentum": 75.0,
      "liquidity": 33.66,
      "wall_signal": false,
      "price": 0.06558
    },
    {
      "symbol": "BILL/USD",
      "score": 59.21,
      "trend": 80.0,
      "momentum": 75.0,
      "liquidity": 23.01,
      "wall_signal": false,
      "price": 0.06556
    },
    {
      "symbol": "ADI/USDT",
      "score": 57.0,
      "trend": 100.0,
      "momentum": 44.83,
      "liquidity": 31.73,
      "wall_signal": false,
      "price": 7.0276
    },
    {
      "symbol": "UNI/USDT",
      "score": 50.85,
      "trend": 100.0,
      "momentum": 26.63,
      "liquidity": 28.43,
      "wall_signal": false,
      "price": 3.604
    },
    {
      "symbol": "AAVE/USDT",
      "score": 50.59,
      "trend": 100.0,
      "momentum": 25.69,
      "liquidity": 29.09,
      "wall_signal": false,
      "price": 96.207
    },
    {
      "symbol": "UNI/USD",
      "score": 49.28,
      "trend": 100.0,
      "momentum": 26.37,
      "liquidity": 18.94,
      "wall_signal": false,
      "price": 3.599
    },
    {
      "symbol": "NEAR/USD",
      "score": 48.42,
      "trend": 81.56,
      "momentum": 37.69,
      "liquidity": 20.65,
      "wall_signal": false,
      "price": 1.986
    },
    {
      "symbol": "ZEC/USDT",
      "score": 45.36,
      "trend": 86.2,
      "momentum": 23.56,
      "liquidity": 28.15,
      "wall_signal": false,
      "price": 503.985
    },
    {
      "symbol": "NEAR/USDT",
      "score": 44.84,
      "trend": 61.56,
      "momentum": 37.9,
      "liquidity": 29.94,
      "wall_signal": false,
      "price": 1.9877
    },
    {
      "symbol": "ZEC/USD",
      "score": 43.67,
      "trend": 86.21,
      "momentum": 23.53,
      "liquidity": 21.57,
      "wall_signal": false,
      "price": 503.6
    },
    {
      "symbol": "USDC/USDT",
      "score": 42.69,
      "trend": 80.0,
      "momentum": 10.21,
      "liquidity": 25.51,
      "wall_signal": false,
      "price": 1.0009
    },
    {
      "symbol": "SOL/USD",
      "score": 42.6,
      "trend": 45.0,
      "momentum": 9.24,
      "liquidity": 19.05,
      "wall_signal": true,
      "price": 74.99
    },
    {
      "symbol": "LINK/USD",
      "score": 42.27,
      "trend": 85.0,
      "momentum": 15.13,
      "liquidity": 22.13,
      "wall_signal": false,
      "price": 7.916
    },
    {
      "symbol": "ETH/USDT",
      "score": 41.75,
      "trend": 85.0,
      "momentum": 15.06,
      "liquidity": 20.05,
      "wall_signal": false,
      "price": 1785.91
    },
    {
      "symbol": "OKB/USDT",
      "score": 41.55,
      "trend": 85.0,
      "momentum": 13.26,
      "liquidity": 21.27,
      "wall_signal": false,
      "price": 80.25
    },
    {
      "symbol": "ETH/USD",
      "score": 40.99,
      "trend": 85.0,
      "momentum": 15.04,
      "liquidity": 21.3,
      "wall_signal": false,
      "price": 1784.1
    },
    {
      "symbol": "USDG/USDT",
      "score": 39.39,
      "trend": 60.0,
      "momentum": 10.27,
      "liquidity": 11.25,
      "wall_signal": true,
      "price": 1.0011
    },
    {
      "symbol": "SUI/USD",
      "score": 37.63,
      "trend": 45.0,
      "momentum": 12.18,
      "liquidity": 20.62,
      "wall_signal": true,
      "price": 0.7299
    },
    {
      "symbol": "ALLO/USDT",
      "score": 36.93,
      "trend": 65.0,
      "momentum": 14.7,
      "liquidity": 12.04,
      "wall_signal": false,
      "price": 0.37934
    },
    {
      "symbol": "ALLO/USD",
      "score": 36.39,
      "trend": 65.0,
      "momentum": 14.84,
      "liquidity": 11.25,
      "wall_signal": false,
      "price": 0.3788
    }
  ]
}